adme_predict/__init__.py
adme_predict/run.py
adme_predict-0.9.dist-info/LICENSE
adme_predict-0.9.dist-info/METADATA
adme_predict-0.9.dist-info/WHEEL
adme_predict-0.9.dist-info/top_level.txt
adme_predict-0.9.dist-info/RECORD
