Metadata-Version: 2.1
Name: adme-predict
Version: 0.9
Summary: Our package is used for ADME attribute prediction
Home-page: https://github.com/pypa/sampleproject
Author: zhuyang
Author-email: zhuyang0925@163.com
License: UNKNOWN
Platform: UNKNOWN
Classifier: Programming Language :: Python :: 2
Classifier: License :: OSI Approved :: MIT License
Classifier: Operating System :: OS Independent
Requires-Python: >=2.6
